timeslot/__init__.py
timeslot/timeslot.py
timeslot-0.1.1.dist-info/WHEEL
timeslot-0.1.1.dist-info/METADATA
timeslot-0.1.1.dist-info/RECORD
