Metadata-Version: 2.1
Name: timeslot
Version: 0.1.1
Summary: Data type for representing time slots with a start and end.
Home-page: https://github.com/ErikBjare/timeslot
License: MIT
Author: Erik Bjäreholt
Author-email: erik@bjareho.lt
Requires-Python: >=3.6,<4.0
Classifier: License :: OSI Approved :: MIT License
Classifier: Programming Language :: Python :: 3
Classifier: Programming Language :: Python :: 3.6
Classifier: Programming Language :: Python :: 3.7
Classifier: Programming Language :: Python :: 3.8
Classifier: Programming Language :: Python :: 3.9
